{
  "version": "7",
  "dialect": "postgresql",
  "entries": [
    {
      "idx": 0,
      "version": "7",
      "when": 1768120456324,
      "tag": "0000_flat_shinko_yamashiro",
      "breakpoints": true
    },
    {
      "idx": 1,
      "version": "7",
      "when": 1768120550371,
      "tag": "0001_left_impossible_man",
      "breakpoints": true
    },
    {
      "idx": 2,
      "version": "7",
      "when": 1768575082701,
      "tag": "0002_kind_the_twelve",
      "breakpoints": true
    }
  ]
}
